{"baseVersion":"1.0.0","diffBundleDex":true,"patches":[{"bundles":[{"applicationName":"android.taobao.atlas.startup.AtlasBridgeApplication","baseVersion":"1.0.0","mainBundle":true,"name":"libcom_taobao_maindex","newBundle":false,"pkgName":"com.multiapk","reset":false,"srcUnitTag":"6b16971778fd30ac067cf6b57e5c670f","unitTag":"6b16971778fd30ac067cf6b57e5c670f","version":"1.0.0"},{"applicationName":"com.multiapk.modules.computer.ComputerApplication","artifactId":"module-computer","dependency":[],"mainBundle":false,"newBundle":false,"pkgName":"com.multiapk.modules.computer","reset":false,"srcUnitTag":"eaedb22d0216b8aff201b82b7de3b8e9","unitTag":"eaedb22d0216b8aff201b82b7de3b8e9","version":"1.0.0"}],"fileName":"patch-1.0.0@1.0.0.tpatch","patchVersion":"1.0.0","targetVersion":"1.0.0"}]}